puremagic/__init__.py
puremagic/__main__.py
puremagic/magic_data.json
puremagic/main.py
puremagic/py.typed
puremagic-1.28.dist-info/LICENSE
puremagic-1.28.dist-info/METADATA
puremagic-1.28.dist-info/WHEEL
puremagic-1.28.dist-info/top_level.txt
puremagic-1.28.dist-info/RECORD
