Metadata-Version: 1.1
Name: puremagic
Version: 1.28
Summary: Pure python implementation of magic file detection
Home-page: https://github.com/cdgriffith/puremagic
Author: Chris Griffith
Author-email: chris@cdgriffith.com
License: MIT
Platform: any
Classifier: Programming Language :: Python
Classifier: Programming Language :: Python :: 3
Classifier: Programming Language :: Python :: Implementation :: PyPy
Classifier: Development Status :: 5 - Production/Stable
Classifier: Natural Language :: English
Classifier: Intended Audience :: Developers
Classifier: License :: OSI Approved :: MIT License
Classifier: Operating System :: OS Independent
Classifier: Topic :: Utilities
